{"type": "FeatureCollection","features": [{"type":"Feature","geometry":{"type":"Point","coordinates":[-1.5405,53.79207]},"properties":{"deviceName":"adeunis1","gtw-id":"aql-DC6","rssi":-108,"snr":2.8,"timestamp":"2018-08-02T13:05:14.178381Z","marker-color":"#692ee6"}}]}