{"type": "FeatureCollection","features": [{"type":"Feature","geometry":{"type":"Point","coordinates":[-1.5405,53.7926]},"properties":{"deviceName":"adeunis1","gtw-id":"aql-DC6","rssi":-115,"snr":-6.2,"timestamp":"2018-08-02T10:25:31.615696Z","marker-color":"#710ede"}},
{"type":"Feature","geometry":{"type":"Point","coordinates":[-1.54067,53.79245]},"properties":{"deviceName":"adeunis1","gtw-id":"aql-DC6","rssi":-104,"snr":-5.8,"timestamp":"2018-08-02T10:26:31.950043Z","marker-color":"#6441eb"}},
{"type":"Feature","geometry":{"type":"Point","coordinates":[-1.54067,53.79235]},"properties":{"deviceName":"adeunis1","gtw-id":"aql-DC6","rssi":-104,"snr":6.5,"timestamp":"2018-08-02T10:27:01.994826Z","marker-color":"#6441eb"}},
{"type":"Feature","geometry":{"type":"Point","coordinates":[-1.54067,53.79232]},"properties":{"deviceName":"adeunis1","gtw-id":"aql-DC6","rssi":-109,"snr":-6.5,"timestamp":"2018-08-02T10:27:40.67464Z","marker-color":"#6a2ae5"}},
{"type":"Feature","geometry":{"type":"Point","coordinates":[-1.5405,53.79238]},"properties":{"deviceName":"adeunis1","gtw-id":"aql-DC6","rssi":-108,"snr":-5.8,"timestamp":"2018-08-02T10:28:05.605928Z","marker-color":"#692ee6"}},
{"type":"Feature","geometry":{"type":"Point","coordinates":[-1.5405,53.79262]},"properties":{"deviceName":"adeunis1","gtw-id":"aql-DC6","rssi":-114,"snr":-8.2,"timestamp":"2018-08-02T10:28:36.615031Z","marker-color":"#7013df"}},
{"type":"Feature","geometry":{"type":"Point","coordinates":[-1.54067,53.79255]},"properties":{"deviceName":"adeunis1","gtw-id":"aql-DC6","rssi":-110,"snr":2.2,"timestamp":"2018-08-02T10:29:31.939645Z","marker-color":"#6b25e4"}},
{"type":"Feature","geometry":{"type":"Point","coordinates":[-1.541,53.7925]},"properties":{"deviceName":"adeunis1","gtw-id":"aql-DC6","rssi":-114,"snr":-3.8,"timestamp":"2018-08-02T10:30:01.984435Z","marker-color":"#7013df"}},
{"type":"Feature","geometry":{"type":"Point","coordinates":[-1.54067,53.79242]},"properties":{"deviceName":"adeunis1","gtw-id":"aql-DC6","rssi":-114,"snr":-14,"timestamp":"2018-08-02T10:31:03.176002Z","marker-color":"#7013df"}},
{"type":"Feature","geometry":{"type":"Point","coordinates":[-1.54067,53.79233]},"properties":{"deviceName":"adeunis1","gtw-id":"aql-DC6","rssi":-97,"snr":-8.5,"timestamp":"2018-08-02T10:31:33.340625Z","marker-color":"#595feb"}},
{"type":"Feature","geometry":{"type":"Point","coordinates":[-1.5405,53.79237]},"properties":{"deviceName":"adeunis1","gtw-id":"aql-DC6","rssi":-111,"snr":0,"timestamp":"2018-08-02T10:32:01.601502Z","marker-color":"#6c20e2"}},
{"type":"Feature","geometry":{"type":"Point","coordinates":[-1.54083,53.79225]},"properties":{"deviceName":"adeunis1","gtw-id":"aql-DC6","rssi":-109,"snr":1.2,"timestamp":"2018-08-02T10:33:01.935852Z","marker-color":"#6a2ae5"}},
{"type":"Feature","geometry":{"type":"Point","coordinates":[-1.54067,53.79228]},"properties":{"deviceName":"adeunis1","gtw-id":"aql-DC6","rssi":-109,"snr":2,"timestamp":"2018-08-02T10:33:31.966603Z","marker-color":"#6a2ae5"}},
{"type":"Feature","geometry":{"type":"Point","coordinates":[-1.5405,53.79232]},"properties":{"deviceName":"adeunis1","gtw-id":"aql-DC6","rssi":-115,"snr":-5.2,"timestamp":"2018-08-02T10:34:01.585324Z","marker-color":"#710ede"}},
{"type":"Feature","geometry":{},"properties":{"deviceName":"adeunis1","gtw-id":"aql-DC6","rssi":-110,"snr":2,"marker-color":"#6b25e4"}},
{"type":"Feature","geometry":{"type":"Point","coordinates":[-1.54117,53.79245]},"properties":{"deviceName":"adeunis1","gtw-id":"aql-DC6","rssi":-108,"snr":3,"timestamp":"2018-08-02T10:35:31.961287Z","marker-color":"#692ee6"}},
{"type":"Feature","geometry":{"type":"Point","coordinates":[-1.54083,53.79267]},"properties":{"deviceName":"adeunis1","gtw-id":"aql-DC6","rssi":-104,"snr":-1.2,"timestamp":"2018-08-02T10:36:06.579178Z","marker-color":"#6441eb"}}]}