{"type": "FeatureCollection","features": [{"type":"Feature","geometry":{"type":"Point","coordinates":[-1.54033,53.79248]},"properties":{"deviceName":"adeunis1","gtw-id":"aql-DC6","rssi":-115,"snr":-6.5,"marker-color":"#710ede"}},
{"type":"Feature","geometry":{"type":"Point","coordinates":[-1.5405,53.7925]},"properties":{"deviceName":"adeunis1","gtw-id":"aql-DC6","rssi":-106,"snr":3.5,"marker-color":"#6738e8"}},
{"type":"Feature","geometry":{"type":"Point","coordinates":[-1.5405,53.79253]},"properties":{"deviceName":"adeunis1","gtw-id":"aql-DC6","rssi":-107,"snr":-1,"marker-color":"#6833e7"}},
{"type":"Feature","geometry":{"type":"Point","coordinates":[-1.5405,53.79253]},"properties":{"deviceName":"adeunis1","gtw-id":"aql-DC6","rssi":-105,"snr":1.8,"marker-color":"#653ce9"}},
{"type":"Feature","geometry":{"type":"Point","coordinates":[-1.5405,53.79255]},"properties":{"deviceName":"adeunis1","gtw-id":"aql-DC6","rssi":-111,"snr":2.2,"marker-color":"#6c20e2"}},
{"type":"Feature","geometry":{"type":"Point","coordinates":[-1.5405,53.79253]},"properties":{"deviceName":"adeunis1","gtw-id":"aql-DC6","rssi":-111,"snr":2.2,"marker-color":"#6c20e2"}}]}