{"type": "FeatureCollection","features": [{"type":"Feature","geometry":{"type":"Point","coordinates":[-1.53367,53.79503]},"properties":{"deviceName":"adeunis1","gtw-id":"aql-DC6","rssi":-115,"snr":-1,"timestamp":"2018-08-02T13:46:51.241559Z","marker-color":"#710ede"}},
{"type":"Feature","geometry":{"type":"Point","coordinates":[-1.531,53.79655]},"properties":{"deviceName":"adeunis1","gtw-id":"aql-DC6","rssi":-118,"snr":-2,"timestamp":"2018-08-02T13:47:53.232963Z","marker-color":"#7400da"}},
{"type":"Feature","geometry":{"type":"Point","coordinates":[-1.52933,53.79805]},"properties":{"deviceName":"adeunis1","gtw-id":"aql-DC6","rssi":-118,"snr":-6.8,"timestamp":"2018-08-02T13:48:46.231555Z","marker-color":"#7400da"}}]}