{"type": "FeatureCollection","features": [{"type":"Feature","geometry":{"type":"Point","coordinates":[-1.53367,53.79503]},"properties":{"deviceName":"adeunis1","gtw-id":"aql-DC6","rssi":-115,"snr":-1,"timestamp":"2018-08-02T13:46:51.241559Z","marker-color":"#710ede"}}]}