{"type": "FeatureCollection","features": [{"type":"Feature","geometry":{"type":"Point","coordinates":[-1.54033,53.79248]},"properties":{"deviceName":"adeunis1","gtw-id":"aql-DC6","rssi":-115,"snr":-6.5,"marker-color":"#710ede"}},
{"type":"Feature","geometry":{"type":"Point","coordinates":[-1.5405,53.7925]},"properties":{"deviceName":"adeunis1","gtw-id":"aql-DC6","rssi":-106,"snr":3.5,"marker-color":"#6738e8"}}]}