{"type": "FeatureCollection","features": [{"type":"Feature","geometry":{"type":"Point","coordinates":[-1.543,53.79167]},"properties":{"deviceName":"adeunis1","gtw-id":"aql-DC6","rssi":-114,"snr":-7.2,"timestamp":"2018-08-01T16:15:37.844Z","marker-color":"#7013df"}}]}