{"type": "FeatureCollection","features": [{"type":"Feature","geometry":{"type":"Point","coordinates":[-1.543,53.79167]},"properties":{"deviceName":"adeunis1","gtw-id":"aql-DC6","rssi":-114,"snr":-7.2,"timestamp":"2018-08-01T16:15:37.844Z","marker-color":"#7013df"}},
{"type":"Feature","geometry":{"type":"Point","coordinates":[-1.5455,53.78812]},"properties":{"deviceName":"adeunis1","gtw-id":"aql-DC6","rssi":-115,"snr":-11,"timestamp":"2018-08-01T16:16:44.844Z","marker-color":"#710ede"}}]}