{"type": "FeatureCollection","features": [{"type":"Feature","geometry":{"type":"Point","coordinates":[-1.543,53.79167]},"properties":{"deviceName":"adeunis1","gtw-id":"aql-DC6","rssi":-114,"snr":-7.2,"timestamp":"2018-08-01T16:15:37.844Z","marker-color":"#7013df"}},
{"type":"Feature","geometry":{"type":"Point","coordinates":[-1.5455,53.78812]},"properties":{"deviceName":"adeunis1","gtw-id":"aql-DC6","rssi":-115,"snr":-11,"timestamp":"2018-08-01T16:16:44.844Z","marker-color":"#710ede"}},
{"type":"Feature","geometry":{"type":"Point","coordinates":[-1.55,53.78627]},"properties":{"deviceName":"adeunis1","gtw-id":"aql-DC6","rssi":-111,"snr":-17.5,"timestamp":"2018-08-01T16:18:10.851Z","marker-color":"#6c20e2"}},
{"type":"Feature","geometry":{"type":"Point","coordinates":[-1.5585,53.78872]},"properties":{"deviceName":"adeunis1","gtw-id":"aql-DC6","rssi":-114,"snr":-12.8,"timestamp":"2018-08-01T16:18:44.834Z","marker-color":"#7013df"}},
{"type":"Feature","geometry":{"type":"Point","coordinates":[-1.56467,53.79122]},"properties":{"deviceName":"adeunis1","gtw-id":"aql-DC6","rssi":-113,"snr":-13.5,"timestamp":"2018-08-01T16:30:05.797Z","marker-color":"#6e17e0"}},
{"type":"Feature","geometry":{"type":"Point","coordinates":[-1.55933,53.79325]},"properties":{"deviceName":"adeunis1","gtw-id":"aql-DC6","rssi":-113,"snr":-13.5,"timestamp":"2018-08-01T16:30:37.794Z","marker-color":"#6e17e0"}},
{"type":"Feature","geometry":{"type":"Point","coordinates":[-1.55617,53.79247]},"properties":{"deviceName":"adeunis1","gtw-id":"aql-DC6","rssi":-115,"snr":-16.5,"timestamp":"2018-08-01T16:31:54.790Z","marker-color":"#710ede"}},
{"type":"Feature","geometry":{"type":"Point","coordinates":[-1.55417,53.79238]},"properties":{"deviceName":"adeunis1","gtw-id":"aql-DC6","rssi":-114,"snr":-17.8,"timestamp":"2018-08-01T16:32:37.779Z","marker-color":"#7013df"}},
{"type":"Feature","geometry":{"type":"Point","coordinates":[-1.553,53.79225]},"properties":{"deviceName":"adeunis1","gtw-id":"aql-DC6","rssi":-115,"snr":-14.5,"timestamp":"2018-08-01T16:33:37.783Z","marker-color":"#710ede"}},
{"type":"Feature","geometry":{"type":"Point","coordinates":[-1.5515,53.79188]},"properties":{"deviceName":"adeunis1","gtw-id":"aql-DC6","rssi":-115,"snr":-14.5,"timestamp":"2018-08-01T16:34:43.776Z","marker-color":"#710ede"}},
{"type":"Feature","geometry":{"type":"Point","coordinates":[-1.54917,53.79205]},"properties":{"deviceName":"adeunis1","gtw-id":"aql-DC6","rssi":-113,"snr":-19.2,"timestamp":"2018-08-01T16:35:37.773Z","marker-color":"#6e17e0"}},
{"type":"Feature","geometry":{"type":"Point","coordinates":[-1.5485,53.79217]},"properties":{"deviceName":"adeunis1","gtw-id":"aql-DC6","rssi":-115,"snr":-11.5,"timestamp":"2018-08-01T16:36:37.776Z","marker-color":"#710ede"}},
{"type":"Feature","geometry":{"type":"Point","coordinates":[-1.54767,53.79223]},"properties":{"deviceName":"adeunis1","gtw-id":"aql-DC6","rssi":-114,"snr":-9.2,"timestamp":"2018-08-01T16:37:37.770Z","marker-color":"#7013df"}},
{"type":"Feature","geometry":{"type":"Point","coordinates":[-1.54417,53.79122]},"properties":{"deviceName":"adeunis1","gtw-id":"aql-DC6","rssi":-115,"snr":-7.8,"timestamp":"2018-08-01T16:38:37.761Z","marker-color":"#710ede"}},
{"type":"Feature","geometry":{"type":"Point","coordinates":[-1.54,53.79062]},"properties":{"deviceName":"adeunis1","gtw-id":"aql-DC6","rssi":-112,"snr":2,"timestamp":"2018-08-01T16:39:37.771Z","marker-color":"#6d1ce1"}},
{"type":"Feature","geometry":{"type":"Point","coordinates":[-1.5345,53.7939]},"properties":{"deviceName":"adeunis1","gtw-id":"aql-DC6","rssi":-113,"snr":-12.2,"timestamp":"2018-08-01T16:40:43.766Z","marker-color":"#6e17e0"}},
{"type":"Feature","geometry":{"type":"Point","coordinates":[-1.533,53.79537]},"properties":{"deviceName":"adeunis1","gtw-id":"aql-DC6","rssi":-112,"snr":-12.2,"timestamp":"2018-08-01T16:41:37.752Z","marker-color":"#6d1ce1"}}]}