{"type": "FeatureCollection","features": [{"type":"Feature","geometry":{"type":"Point","coordinates":[-1.5405,53.7926]},"properties":{"deviceName":"adeunis1","gtw-id":"aql-DC6","rssi":-115,"snr":-6.2,"timestamp":"2018-08-02T10:25:31.615696Z","marker-color":"#710ede"}},
{"type":"Feature","geometry":{"type":"Point","coordinates":[-1.54067,53.79245]},"properties":{"deviceName":"adeunis1","gtw-id":"aql-DC6","rssi":-104,"snr":-5.8,"timestamp":"2018-08-02T10:26:31.950043Z","marker-color":"#6441eb"}},
{"type":"Feature","geometry":{"type":"Point","coordinates":[-1.54067,53.79235]},"properties":{"deviceName":"adeunis1","gtw-id":"aql-DC6","rssi":-104,"snr":6.5,"timestamp":"2018-08-02T10:27:01.994826Z","marker-color":"#6441eb"}}]}