{"type": "FeatureCollection","features": [{"type":"Feature","geometry":{"type":"Point","coordinates":[-1.5405,53.79207]},"properties":{"deviceName":"adeunis1","gtw-id":"aql-DC6","rssi":-108,"snr":2.8,"timestamp":"2018-08-02T13:05:14.178381Z","marker-color":"#692ee6"}},
{"type":"Feature","geometry":{"type":"Point","coordinates":[-1.5405,53.7923]},"properties":{"deviceName":"adeunis1","gtw-id":"aql-DC6","rssi":-108,"snr":2,"timestamp":"2018-08-02T13:05:43.797097Z","marker-color":"#692ee6"}},
{"type":"Feature","geometry":{"type":"Point","coordinates":[-1.54067,53.79212]},"properties":{"deviceName":"adeunis1","gtw-id":"aql-DC6","rssi":-102,"snr":-2.8,"timestamp":"2018-08-02T13:06:44.135352Z","marker-color":"#624aed"}},
{"type":"Feature","geometry":{"type":"Point","coordinates":[-1.54,53.7927]},"properties":{"deviceName":"adeunis1","gtw-id":"aql-DC6","rssi":-110,"snr":1.8,"timestamp":"2018-08-02T13:07:14.180134Z","marker-color":"#6b25e4"}},
{"type":"Feature","geometry":{"type":"Point","coordinates":[-1.54,53.79275]},"properties":{"deviceName":"adeunis1","gtw-id":"aql-DC6","rssi":-108,"snr":5.2,"timestamp":"2018-08-02T13:07:43.798867Z","marker-color":"#692ee6"}},
{"type":"Feature","geometry":{"type":"Point","coordinates":[-1.54033,53.79225]},"properties":{"deviceName":"adeunis1","gtw-id":"aql-DC6","rssi":-110,"snr":2.8,"timestamp":"2018-08-02T13:08:44.138081Z","marker-color":"#6b25e4"}}]}