{"type": "FeatureCollection","features": [{"type":"Feature","geometry":{"type":"Point","coordinates":[-1.53367,53.79503]},"properties":{"deviceName":"adeunis1","gtw-id":"aql-DC6","rssi":-115,"snr":-1,"timestamp":"2018-08-02T13:46:51.241559Z","marker-color":"#710ede"}},
{"type":"Feature","geometry":{"type":"Point","coordinates":[-1.531,53.79655]},"properties":{"deviceName":"adeunis1","gtw-id":"aql-DC6","rssi":-118,"snr":-2,"timestamp":"2018-08-02T13:47:53.232963Z","marker-color":"#7400da"}},
{"type":"Feature","geometry":{"type":"Point","coordinates":[-1.52933,53.79805]},"properties":{"deviceName":"adeunis1","gtw-id":"aql-DC6","rssi":-118,"snr":-6.8,"timestamp":"2018-08-02T13:48:46.231555Z","marker-color":"#7400da"}},
{"type":"Feature","geometry":{"type":"Point","coordinates":[-1.5175,53.79787]},"properties":{"deviceName":"adeunis1","gtw-id":"aql-DC6","rssi":-115,"snr":-0.2,"timestamp":"2018-08-02T13:49:59.217748Z","marker-color":"#710ede"}},
{"type":"Feature","geometry":{"type":"Point","coordinates":[-1.50767,53.7993]},"properties":{"deviceName":"adeunis1","gtw-id":"aql-DC6","rssi":-117,"snr":-7,"timestamp":"2018-08-02T13:50:46.220401Z","marker-color":"#7305db"}},
{"type":"Feature","geometry":{"type":"Point","coordinates":[-1.4965,53.80165]},"properties":{"deviceName":"adeunis1","gtw-id":"aql-DC6","rssi":-119,"snr":-15.8,"timestamp":"2018-08-02T13:51:58.21777Z","marker-color":"#7500d8"}},
{"type":"Feature","geometry":{"type":"Point","coordinates":[-1.48117,53.80398]},"properties":{"deviceName":"adeunis1","gtw-id":"aql-DC6","rssi":-118,"snr":-14.8,"timestamp":"2018-08-02T13:55:22.212087Z","marker-color":"#7400da"}},
{"type":"Feature","geometry":{"type":"Point","coordinates":[-1.48,53.80432]},"properties":{"deviceName":"adeunis1","gtw-id":"aql-DC6","rssi":-116,"snr":-14.8,"timestamp":"2018-08-02T13:56:21.20185Z","marker-color":"#7209dc"}},
{"type":"Feature","geometry":{"type":"Point","coordinates":[-1.4665,53.8083]},"properties":{"deviceName":"adeunis1","gtw-id":"aql-DC6","rssi":-118,"snr":-17.8,"timestamp":"2018-08-02T13:58:30.194204Z","marker-color":"#7400da"}},
{"type":"Feature","geometry":{"type":"Point","coordinates":[-1.45617,53.81325]},"properties":{"deviceName":"adeunis1","gtw-id":"aql-DC6","rssi":-115,"snr":-4.5,"timestamp":"2018-08-02T13:59:25.202373Z","marker-color":"#710ede"}},
{"type":"Feature","geometry":{"type":"Point","coordinates":[-1.45567,53.81358]},"properties":{"deviceName":"adeunis1","gtw-id":"aql-DC6","rssi":-119,"snr":-10.8,"timestamp":"2018-08-02T13:59:46.195112Z","marker-color":"#7500d8"}},
{"type":"Feature","geometry":{"type":"Point","coordinates":[-1.46517,53.80873]},"properties":{"deviceName":"adeunis1","gtw-id":"aql-DC6","rssi":-118,"snr":-11.8,"timestamp":"2018-08-02T14:00:46.198154Z","marker-color":"#7400da"}},
{"type":"Feature","geometry":{"type":"Point","coordinates":[-1.47333,53.80645]},"properties":{"deviceName":"adeunis1","gtw-id":"aql-DC6","rssi":-118,"snr":-7.2,"timestamp":"2018-08-02T14:01:46.181061Z","marker-color":"#7400da"}},
{"type":"Feature","geometry":{"type":"Point","coordinates":[-1.47867,53.8042]},"properties":{"deviceName":"adeunis1","gtw-id":"aql-DC6","rssi":-119,"snr":-15.2,"timestamp":"2018-08-02T14:03:26.18245Z","marker-color":"#7500d8"}}]}