{"type": "FeatureCollection","features": [{"type":"Feature","geometry":{"type":"Point","coordinates":[-1.5405,53.79207]},"properties":{"deviceName":"adeunis1","gtw-id":"aql-DC6","rssi":-108,"snr":2.8,"timestamp":"2018-08-02T13:05:14.178381Z","marker-color":"#692ee6"}},
{"type":"Feature","geometry":{"type":"Point","coordinates":[-1.5405,53.7923]},"properties":{"deviceName":"adeunis1","gtw-id":"aql-DC6","rssi":-108,"snr":2,"timestamp":"2018-08-02T13:05:43.797097Z","marker-color":"#692ee6"}},
{"type":"Feature","geometry":{"type":"Point","coordinates":[-1.54067,53.79212]},"properties":{"deviceName":"adeunis1","gtw-id":"aql-DC6","rssi":-102,"snr":-2.8,"timestamp":"2018-08-02T13:06:44.135352Z","marker-color":"#624aed"}},
{"type":"Feature","geometry":{"type":"Point","coordinates":[-1.54,53.7927]},"properties":{"deviceName":"adeunis1","gtw-id":"aql-DC6","rssi":-110,"snr":1.8,"timestamp":"2018-08-02T13:07:14.180134Z","marker-color":"#6b25e4"}},
{"type":"Feature","geometry":{"type":"Point","coordinates":[-1.54,53.79275]},"properties":{"deviceName":"adeunis1","gtw-id":"aql-DC6","rssi":-108,"snr":5.2,"timestamp":"2018-08-02T13:07:43.798867Z","marker-color":"#692ee6"}},
{"type":"Feature","geometry":{"type":"Point","coordinates":[-1.54033,53.79225]},"properties":{"deviceName":"adeunis1","gtw-id":"aql-DC6","rssi":-110,"snr":2.8,"timestamp":"2018-08-02T13:08:44.138081Z","marker-color":"#6b25e4"}},
{"type":"Feature","geometry":{"type":"Point","coordinates":[-1.5405,53.79233]},"properties":{"deviceName":"adeunis1","gtw-id":"aql-DC6","rssi":-104,"snr":5.8,"timestamp":"2018-08-02T13:09:14.167855Z","marker-color":"#6441eb"}},
{"type":"Feature","geometry":{"type":"Point","coordinates":[-1.5405,53.79237]},"properties":{"deviceName":"adeunis1","gtw-id":"aql-DC6","rssi":-107,"snr":3.2,"timestamp":"2018-08-02T13:09:43.7867Z","marker-color":"#6833e7"}},
{"type":"Feature","geometry":{"type":"Point","coordinates":[-1.5405,53.79232]},"properties":{"deviceName":"adeunis1","gtw-id":"aql-DC6","rssi":-111,"snr":2,"timestamp":"2018-08-02T13:10:13.787058Z","marker-color":"#6c20e2"}},
{"type":"Feature","geometry":{"type":"Point","coordinates":[-1.54067,53.79255]},"properties":{"deviceName":"adeunis1","gtw-id":"aql-DC6","rssi":-111,"snr":0.8,"timestamp":"2018-08-02T13:11:14.120327Z","marker-color":"#6c20e2"}},
{"type":"Feature","geometry":{"type":"Point","coordinates":[-1.54083,53.79252]},"properties":{"deviceName":"adeunis1","gtw-id":"aql-DC6","rssi":-107,"snr":1.8,"timestamp":"2018-08-02T13:11:44.165109Z","marker-color":"#6833e7"}},
{"type":"Feature","geometry":{"type":"Point","coordinates":[-1.54067,53.79217]},"properties":{"deviceName":"adeunis1","gtw-id":"aql-DC6","rssi":-111,"snr":-0.8,"timestamp":"2018-08-02T13:12:13.783834Z","marker-color":"#6c20e2"}},
{"type":"Feature","geometry":{"type":"Point","coordinates":[-1.5405,53.79253]},"properties":{"deviceName":"adeunis1","gtw-id":"aql-DC6","rssi":-110,"snr":-3,"timestamp":"2018-08-02T13:13:14.123056Z","marker-color":"#6b25e4"}},
{"type":"Feature","geometry":{"type":"Point","coordinates":[-1.54067,53.79252]},"properties":{"deviceName":"adeunis1","gtw-id":"aql-DC6","rssi":-114,"snr":-1.8,"timestamp":"2018-08-02T13:13:44.15283Z","marker-color":"#7013df"}},
{"type":"Feature","geometry":{"type":"Point","coordinates":[-1.5405,53.79255]},"properties":{"deviceName":"adeunis1","gtw-id":"aql-DC6","rssi":-109,"snr":2.2,"timestamp":"2018-08-02T13:14:45.343411Z","marker-color":"#6a2ae5"}},
{"type":"Feature","geometry":{"type":"Point","coordinates":[-1.5405,53.79257]},"properties":{"deviceName":"adeunis1","gtw-id":"aql-DC6","rssi":-104,"snr":0.8,"timestamp":"2018-08-02T13:15:15.508025Z","marker-color":"#6441eb"}},
{"type":"Feature","geometry":{"type":"Point","coordinates":[-1.54067,53.7925]},"properties":{"deviceName":"adeunis1","gtw-id":"aql-DC6","rssi":-114,"snr":1.2,"timestamp":"2018-08-02T13:15:43.768901Z","marker-color":"#7013df"}},
{"type":"Feature","geometry":{"type":"Point","coordinates":[-1.5405,53.79247]},"properties":{"deviceName":"adeunis1","gtw-id":"aql-DC6","rssi":-109,"snr":3,"timestamp":"2018-08-02T13:16:44.108242Z","marker-color":"#6a2ae5"}},
{"type":"Feature","geometry":{"type":"Point","coordinates":[-1.5405,53.7925]},"properties":{"deviceName":"adeunis1","gtw-id":"aql-DC6","rssi":-110,"snr":0.8,"timestamp":"2018-08-02T13:17:14.137897Z","marker-color":"#6b25e4"}},
{"type":"Feature","geometry":{"type":"Point","coordinates":[-1.54017,53.79235]},"properties":{"deviceName":"adeunis1","gtw-id":"aql-DC6","rssi":-107,"snr":4.8,"timestamp":"2018-08-02T13:17:43.756734Z","marker-color":"#6833e7"}}]}